firstpypackage/__init__.py
firstpypackage/add.py
firstpypackage/subtract.py
firstpypackage/extras/__init__.py
firstpypackage/extras/divide.py
firstpypackage/extras/multiply.py
firstpypackage-0.0.1.dist-info/METADATA
firstpypackage-0.0.1.dist-info/WHEEL
firstpypackage-0.0.1.dist-info/top_level.txt
firstpypackage-0.0.1.dist-info/RECORD
