Metadata-Version: 2.1
Name: firstpypackage
Version: 0.0.1
Summary: My first Python package
Home-page: UNKNOWN
Author: Jason Dsouza
Author-email: <jason@email.com>
License: UNKNOWN
Platform: UNKNOWN
